Metadata-Version: 2.4
Name: ableton-mcp-u
Version: 1.0.1
Summary: Ableton Live integration through the Model Context Protocol - Upgraded Version
Author-email: Ahmad M Abdullah <a7madmajdi@gmail.com>
License: MIT
Project-URL: Homepage, https://github.com/AhmadMagdi/ableton-mcp-u
Project-URL: Bug Tracker, https://github.com/AhmadMagdi/ableton-mcp-u/issues
Classifier: Programming Language :: Python :: 3
Classifier: License :: OSI Approved :: MIT License
Classifier: Operating System :: OS Independent
Requires-Python: >=3.10
License-File: LICENSE
Requires-Dist: mcp[cli]>=1.3.0
Dynamic: license-file
